{
	"song": {
		"player1": "agoti_mad_playable",
		"events": [
			[
				26178.4090909091,
				[
					[
						"Change Character",
						"bf",
						"agoti_playable"
					]
				]
			],
			[
				58227.2727272728,
				[
					[
						"Change Character",
						"bf",
						"agoti_mad_playable"
					]
				]
			],
			[
				59938.6363636364,
				[
					[
						"Change Character",
						"bf",
						"agoti_playable"
					]
				]
			]
		],
		"gfVersion": "gf-christmas",
		"player2": "aldryx",
		"notes": [
			{
				"lengthInSteps": 16,
				"sectionNotes": [
					[
						0,
						1,
						0
					],
					[
						818.181818181818,
						1,
						0
					],
					[
						1090.90909090909,
						2,
						0
					],
					[
						1363.63636363636,
						3,
						0
					],
					[
						1636.36363636364,
						1,
						0
					]
				],
				"mustHitSection": true
			},
			{
				"lengthInSteps": 16,
				"sectionNotes": [
					[
						2454.54545454545,
						1,
						0
					],
					[
						2727.27272727273,
						2,
						0
					],
					[
						3000,
						3,
						0
					],
					[
						3272.72727272727,
						0,
						0
					],
					[
						4090.90909090909,
						0,
						0
					]
				],
				"mustHitSection": true
			},
			{
				"lengthInSteps": 16,
				"sectionNotes": [
					[
						4363.63636363636,
						1,
						0
					],
					[
						4636.36363636364,
						2,
						0
					],
					[
						4909.09090909091,
						3,
						0
					],
					[
						5727.27272727273,
						3,
						0
					],
					[
						6000,
						2,
						0
					],
					[
						6272.72727272727,
						0,
						0
					]
				],
				"mustHitSection": true
			},
			{
				"lengthInSteps": 16,
				"sectionNotes": [
					[
						6545.45454545455,
						1,
						0
					],
					[
						7363.63636363636,
						1,
						0
					],
					[
						7636.36363636364,
						2,
						68.1818181818182
					],
					[
						7909.09090909091,
						3,
						0
					],
					[
						8181.81818181818,
						0,
						0
					]
				],
				"mustHitSection": true
			},
			{
				"lengthInSteps": 16,
				"sectionNotes": [
					[
						9000,
						0,
						0
					],
					[
						9272.72727272727,
						1,
						0
					],
					[
						9545.45454545455,
						2,
						0
					],
					[
						9818.18181818182,
						3,
						0
					],
					[
						10636.3636363636,
						3,
						0
					]
				],
				"mustHitSection": true
			},
			{
				"lengthInSteps": 16,
				"sectionNotes": [
					[
						10909.0909090909,
						1,
						0
					],
					[
						11181.8181818182,
						0,
						0
					],
					[
						11454.5454545455,
						2,
						0
					],
					[
						12000,
						3,
						0
					],
					[
						12545.4545454545,
						2,
						0
					],
					[
						12818.1818181818,
						0,
						0
					]
				],
				"mustHitSection": true
			},
			{
				"lengthInSteps": 16,
				"sectionNotes": [
					[
						13090.9090909091,
						1,
						0
					],
					[
						13909.0909090909,
						1,
						0
					],
					[
						14181.8181818182,
						2,
						0
					],
					[
						14454.5454545455,
						3,
						0
					],
					[
						14727.2727272727,
						1,
						0
					]
				],
				"mustHitSection": true
			},
			{
				"lengthInSteps": 16,
				"sectionNotes": [
					[
						15545.4545454545,
						1,
						0
					],
					[
						15818.1818181818,
						2,
						0
					],
					[
						16090.9090909091,
						3,
						0
					],
					[
						16363.6363636364,
						0,
						0
					],
					[
						17181.8181818182,
						0,
						0
					]
				],
				"mustHitSection": true
			},
			{
				"lengthInSteps": 16,
				"sectionNotes": [
					[
						17454.5454545455,
						1,
						0
					],
					[
						17727.2727272727,
						2,
						0
					],
					[
						18000,
						3,
						0
					],
					[
						18818.1818181818,
						3,
						0
					],
					[
						19090.9090909091,
						2,
						0
					],
					[
						19363.6363636364,
						0,
						0
					]
				],
				"mustHitSection": true
			},
			{
				"lengthInSteps": 16,
				"sectionNotes": [
					[
						19636.3636363636,
						1,
						0
					],
					[
						20454.5454545455,
						1,
						0
					],
					[
						21272.7272727273,
						0,
						0
					],
					[
						21000,
						3,
						0
					],
					[
						20727.2727272727,
						2,
						0
					]
				],
				"mustHitSection": true
			},
			{
				"lengthInSteps": 16,
				"sectionNotes": [
					[
						22090.9090909091,
						0,
						0
					],
					[
						22363.6363636364,
						1,
						0
					],
					[
						22636.3636363636,
						2,
						0
					],
					[
						22909.0909090909,
						3,
						0
					],
					[
						23727.2727272727,
						3,
						0
					]
				],
				"mustHitSection": true
			},
			{
				"lengthInSteps": 16,
				"sectionNotes": [
					[
						24000,
						1,
						0
					],
					[
						24272.7272727273,
						0,
						0
					],
					[
						24545.4545454545,
						2,
						0
					],
					[
						25090.9090909091,
						3,
						0
					],
					[
						25636.3636363636,
						2,
						0
					],
					[
						25909.0909090909,
						0,
						0
					]
				],
				"mustHitSection": true
			},
			{
				"lengthInSteps": 16,
				"sectionNotes": [
					[
						26181.8181818182,
						1,
						0
					],
					[
						27272.7272727273,
						3,
						0
					],
					[
						27545.4545454546,
						0,
						0
					],
					[
						27000,
						2,
						0
					],
					[
						27818.1818181818,
						1,
						0
					]
				],
				"mustHitSection": true
			},
			{
				"lengthInSteps": 16,
				"sectionNotes": [
					[
						28909.0909090909,
						2,
						0
					],
					[
						29181.8181818182,
						3,
						0
					],
					[
						29454.5454545455,
						0,
						0
					],
					[
						28636.3636363636,
						1,
						0
					],
					[
						30272.7272727273,
						0,
						0
					]
				],
				"mustHitSection": true
			},
			{
				"lengthInSteps": 16,
				"sectionNotes": [
					[
						30545.4545454546,
						1,
						0
					],
					[
						30818.1818181818,
						2,
						0
					],
					[
						31090.9090909091,
						3,
						0
					],
					[
						31909.0909090909,
						3,
						0
					],
					[
						32181.8181818182,
						1,
						0
					],
					[
						32454.5454545455,
						0,
						0
					]
				],
				"mustHitSection": true
			},
			{
				"lengthInSteps": 16,
				"sectionNotes": [
					[
						32727.2727272727,
						3,
						0
					],
					[
						33818.1818181818,
						2,
						136.363636363636
					],
					[
						33545.4545454546,
						1,
						136.363636363636
					],
					[
						34090.9090909091,
						3,
						136.363636363636
					],
					[
						34363.6363636364,
						0,
						0
					]
				],
				"mustHitSection": true
			},
			{
				"lengthInSteps": 16,
				"sectionNotes": [
					[
						35454.5454545455,
						1,
						0
					],
					[
						35727.2727272727,
						3,
						0
					],
					[
						36000,
						2,
						0
					],
					[
						35181.8181818182,
						0,
						0
					],
					[
						36818.1818181818,
						3,
						0
					]
				],
				"mustHitSection": true
			},
			{
				"lengthInSteps": 16,
				"sectionNotes": [
					[
						37090.9090909091,
						1,
						0
					],
					[
						37363.6363636364,
						0,
						0
					],
					[
						37636.3636363637,
						1,
						0
					],
					[
						38727.2727272727,
						2,
						0
					],
					[
						39000,
						3,
						0
					],
					[
						38181.8181818182,
						0,
						0
					]
				],
				"mustHitSection": true
			},
			{
				"lengthInSteps": 16,
				"sectionNotes": [
					[
						39272.7272727273,
						1,
						0
					],
					[
						40363.6363636364,
						3,
						0
					],
					[
						40636.3636363636,
						0,
						0
					],
					[
						40090.9090909091,
						2,
						0
					],
					[
						40909.0909090909,
						1,
						0
					]
				],
				"mustHitSection": true
			},
			{
				"lengthInSteps": 16,
				"sectionNotes": [
					[
						42000,
						2,
						0
					],
					[
						42272.7272727273,
						3,
						0
					],
					[
						42545.4545454546,
						0,
						0
					],
					[
						41727.2727272727,
						1,
						0
					],
					[
						43363.6363636364,
						0,
						0
					]
				],
				"mustHitSection": true
			},
			{
				"lengthInSteps": 16,
				"sectionNotes": [
					[
						43636.3636363636,
						1,
						0
					],
					[
						43909.0909090909,
						2,
						0
					],
					[
						44181.8181818182,
						3,
						0
					],
					[
						45000,
						3,
						0
					],
					[
						45272.7272727273,
						1,
						0
					],
					[
						45545.4545454546,
						0,
						0
					]
				],
				"mustHitSection": true
			},
			{
				"lengthInSteps": 16,
				"sectionNotes": [
					[
						45818.1818181818,
						3,
						0
					],
					[
						46909.0909090909,
						2,
						136.363636363636
					],
					[
						46636.3636363636,
						1,
						136.363636363636
					],
					[
						47181.8181818182,
						3,
						136.363636363636
					],
					[
						47454.5454545455,
						0,
						0
					]
				],
				"mustHitSection": true
			},
			{
				"lengthInSteps": 16,
				"sectionNotes": [
					[
						48545.4545454546,
						1,
						0
					],
					[
						48818.1818181818,
						3,
						0
					],
					[
						49090.9090909091,
						2,
						0
					],
					[
						48272.7272727273,
						0,
						0
					],
					[
						49909.0909090909,
						3,
						0
					]
				],
				"mustHitSection": true
			},
			{
				"lengthInSteps": 16,
				"sectionNotes": [
					[
						50181.8181818182,
						1,
						0
					],
					[
						50454.5454545455,
						0,
						0
					],
					[
						50727.2727272727,
						1,
						0
					],
					[
						51272.7272727273,
						1,
						0
					],
					[
						51818.1818181819,
						2,
						204.545454545455
					],
					[
						52090.9090909091,
						1,
						136.363636363636
					]
				],
				"mustHitSection": true
			},
			{
				"lengthInSteps": 16,
				"sectionNotes": [
					[
						54000,
						1,
						409.090909090909
					]
				],
				"mustHitSection": true
			},
			{
				"lengthInSteps": 16,
				"sectionNotes": [
					[
						55090.9090909091,
						0,
						409.090909090909
					],
					[
						54818.1818181819,
						1,
						136.363636363636
					],
					[
						54545.4545454546,
						3,
						136.363636363636
					],
					[
						55636.3636363637,
						2,
						954.545454545454
					]
				],
				"mustHitSection": true
			},
			{
				"lengthInSteps": 16,
				"sectionNotes": [
					[
						56727.2727272728,
						1,
						409.090909090909
					],
					[
						57272.7272727273,
						3,
						409.090909090909
					],
					[
						58298.8636363637,
						2,
						0
					],
					[
						58711.3636363637,
						3,
						0
					]
				],
				"mustHitSection": true
			},
			{
				"lengthInSteps": 16,
				"sectionNotes": [
					[
						58909.0909090909,
						3,
						0
					],
					[
						60000,
						1,
						272.727272727273
					],
					[
						60545.4545454546,
						3,
						272.727272727273
					]
				],
				"mustHitSection": true
			},
			{
				"lengthInSteps": 16,
				"sectionNotes": [
					[
						61636.3636363637,
						2,
						545.454545454545
					],
					[
						62454.5454545455,
						0,
						545.454545454545
					]
				],
				"mustHitSection": true
			},
			{
				"lengthInSteps": 16,
				"sectionNotes": [],
				"mustHitSection": true
			},
			{
				"lengthInSteps": 16,
				"sectionNotes": [
					[
						66545.4545454546,
						1,
						0
					],
					[
						66579.5454545455,
						2,
						340.909090909091
					],
					[
						67090.9090909091,
						0,
						409.090909090909
					]
				],
				"mustHitSection": true
			},
			{
				"lengthInSteps": 16,
				"sectionNotes": [
					[
						67636.3636363637,
						3,
						0
					],
					[
						68181.8181818182,
						3,
						0
					],
					[
						68727.2727272728,
						2,
						681.818181818182
					]
				],
				"mustHitSection": true
			},
			{
				"sectionNotes": [
					[
						69818.1818181819,
						1,
						0
					],
					[
						70090.9090909091,
						3,
						0
					],
					[
						70363.6363636364,
						0,
						681.818181818182
					]
				],
				"typeOfSection": 0,
				"lengthInSteps": 16,
				"altAnim": false,
				"mustHitSection": true,
				"changeBPM": false,
				"bpm": 100
			},
			{
				"sectionNotes": [
					[
						72000,
						2,
						681.818181818182
					],
					[
						73636.3636363637,
						3,
						409.090909090909
					]
				],
				"typeOfSection": 0,
				"lengthInSteps": 16,
				"altAnim": false,
				"mustHitSection": true,
				"changeBPM": false,
				"bpm": 200
			},
			{
				"sectionNotes": [
					[
						75272.7272727273,
						0,
						681.818181818182
					]
				],
				"typeOfSection": 0,
				"lengthInSteps": 16,
				"altAnim": false,
				"mustHitSection": true,
				"changeBPM": false,
				"bpm": 200
			},
			{
				"sectionNotes": [
					[
						76909.0909090909,
						1,
						409.090909090909
					]
				],
				"typeOfSection": 0,
				"lengthInSteps": 16,
				"altAnim": false,
				"mustHitSection": true,
				"changeBPM": false,
				"bpm": 200
			},
			{
				"sectionNotes": [
					[
						78545.4545454546,
						2,
						272.727272727273
					],
					[
						79090.9090909091,
						1,
						272.727272727273
					],
					[
						79636.3636363636,
						1,
						272.727272727273
					],
					[
						80181.8181818182,
						3,
						272.727272727273
					]
				],
				"typeOfSection": 0,
				"lengthInSteps": 16,
				"altAnim": false,
				"mustHitSection": true,
				"changeBPM": false,
				"bpm": 200
			},
			{
				"sectionNotes": [
					[
						80727.2727272727,
						3,
						272.727272727273
					],
					[
						81272.7272727273,
						1,
						272.727272727273
					],
					[
						81818.1818181818,
						0,
						136.363636363636
					],
					[
						82363.6363636364,
						2,
						409.090909090909
					]
				],
				"typeOfSection": 0,
				"lengthInSteps": 16,
				"altAnim": false,
				"mustHitSection": true,
				"changeBPM": false,
				"bpm": 200
			},
			{
				"sectionNotes": [
					[
						83181.8181818182,
						3,
						0
					],
					[
						83454.5454545455,
						0,
						0
					]
				],
				"typeOfSection": 0,
				"lengthInSteps": 16,
				"altAnim": false,
				"mustHitSection": true,
				"changeBPM": false,
				"bpm": 200
			},
			{
				"sectionNotes": [
					[
						85090.9090909091,
						2,
						409.090909090909
					],
					[
						85636.3636363636,
						3,
						409.090909090909
					],
					[
						86181.8181818182,
						1,
						409.090909090909
					],
					[
						86727.2727272727,
						0,
						409.090909090909
					]
				],
				"typeOfSection": 0,
				"lengthInSteps": 16,
				"altAnim": false,
				"mustHitSection": true,
				"changeBPM": false,
				"bpm": 200
			},
			{
				"sectionNotes": [
					[
						87272.7272727273,
						2,
						409.090909090909
					],
					[
						87818.1818181818,
						1,
						409.090909090909
					],
					[
						88363.6363636364,
						0,
						409.090909090909
					],
					[
						88909.0909090909,
						3,
						681.818181818182
					]
				],
				"typeOfSection": 0,
				"lengthInSteps": 16,
				"altAnim": false,
				"mustHitSection": true,
				"changeBPM": false,
				"bpm": 200
			},
			{
				"sectionNotes": [
					[
						89727.2727272727,
						0,
						0
					],
					[
						90000,
						1,
						0
					]
				],
				"typeOfSection": 0,
				"lengthInSteps": 16,
				"altAnim": false,
				"mustHitSection": false,
				"changeBPM": false,
				"bpm": 200
			},
			{
				"sectionNotes": [
					[
						91636.3636363636,
						2,
						272.727272727273
					],
					[
						92181.8181818182,
						1,
						272.727272727273
					],
					[
						92727.2727272727,
						1,
						272.727272727273
					],
					[
						93272.7272727273,
						3,
						272.727272727273
					]
				],
				"typeOfSection": 0,
				"lengthInSteps": 16,
				"altAnim": false,
				"mustHitSection": false,
				"changeBPM": false,
				"bpm": 200
			},
			{
				"sectionNotes": [
					[
						93818.1818181818,
						3,
						272.727272727273
					],
					[
						94363.6363636364,
						1,
						272.727272727273
					],
					[
						94909.0909090909,
						0,
						136.363636363636
					],
					[
						95454.5454545455,
						2,
						409.090909090909
					]
				],
				"typeOfSection": 0,
				"lengthInSteps": 16,
				"altAnim": false,
				"mustHitSection": false,
				"changeBPM": false,
				"bpm": 200
			},
			{
				"sectionNotes": [
					[
						96272.7272727273,
						3,
						0
					],
					[
						96545.4545454545,
						0,
						0
					]
				],
				"typeOfSection": 0,
				"lengthInSteps": 16,
				"altAnim": false,
				"mustHitSection": false,
				"changeBPM": false,
				"bpm": 200
			},
			{
				"sectionNotes": [
					[
						98181.8181818182,
						2,
						409.090909090909
					],
					[
						98727.2727272727,
						3,
						409.090909090909
					],
					[
						99272.7272727273,
						1,
						409.090909090909
					],
					[
						99818.1818181818,
						0,
						409.090909090909
					]
				],
				"typeOfSection": 0,
				"lengthInSteps": 16,
				"altAnim": false,
				"mustHitSection": false,
				"changeBPM": false,
				"bpm": 200
			},
			{
				"sectionNotes": [
					[
						100363.636363636,
						2,
						409.090909090909
					],
					[
						100909.090909091,
						1,
						409.090909090909
					],
					[
						101454.545454545,
						0,
						409.090909090909
					],
					[
						102000,
						3,
						681.818181818182
					]
				],
				"typeOfSection": 0,
				"lengthInSteps": 16,
				"altAnim": false,
				"mustHitSection": false,
				"changeBPM": false,
				"bpm": 200
			},
			{
				"sectionNotes": [
					[
						102818.181818182,
						4,
						0
					],
					[
						103090.909090909,
						5,
						0
					],
					[
						103090.909090909,
						1,
						0
					],
					[
						103909.090909091,
						1,
						0
					],
					[
						104181.818181818,
						2,
						0
					],
					[
						104454.545454545,
						3,
						0
					]
				],
				"typeOfSection": 0,
				"lengthInSteps": 16,
				"altAnim": false,
				"mustHitSection": false,
				"changeBPM": false,
				"bpm": 200
			},
			{
				"sectionNotes": [
					[
						104727.272727273,
						1,
						0
					],
					[
						105818.181818182,
						2,
						0
					],
					[
						105545.454545455,
						0,
						0
					],
					[
						106090.909090909,
						3,
						0
					],
					[
						106363.636363636,
						1,
						0
					]
				],
				"typeOfSection": 0,
				"lengthInSteps": 16,
				"altAnim": false,
				"mustHitSection": false,
				"changeBPM": false,
				"bpm": 200
			},
			{
				"sectionNotes": [
					[
						107181.818181818,
						1,
						0
					],
					[
						107454.545454545,
						0,
						0
					],
					[
						107727.272727273,
						2,
						0
					],
					[
						108000,
						3,
						0
					],
					[
						108818.181818182,
						1,
						0
					]
				],
				"typeOfSection": 0,
				"lengthInSteps": 16,
				"altAnim": false,
				"mustHitSection": true,
				"changeBPM": false,
				"bpm": 200
			},
			{
				"sectionNotes": [
					[
						109090.909090909,
						0,
						0
					],
					[
						109363.636363636,
						2,
						0
					],
					[
						109636.363636364,
						3,
						0
					],
					[
						110454.545454545,
						1,
						0
					],
					[
						110727.272727273,
						2,
						136.363636363636
					],
					[
						111000,
						3,
						0
					]
				],
				"typeOfSection": 0,
				"lengthInSteps": 16,
				"altAnim": false,
				"mustHitSection": true,
				"changeBPM": false,
				"bpm": 200
			},
			{
				"sectionNotes": [
					[
						111272.727272727,
						1,
						0
					],
					[
						112636.363636364,
						3,
						0
					],
					[
						112909.090909091,
						0,
						0
					],
					[
						112090.909090909,
						0,
						0
					],
					[
						112363.636363636,
						2,
						0
					]
				],
				"typeOfSection": 0,
				"lengthInSteps": 16,
				"altAnim": false,
				"mustHitSection": true,
				"changeBPM": false,
				"bpm": 200
			},
			{
				"sectionNotes": [
					[
						113727.272727273,
						0,
						0
					],
					[
						114000,
						2,
						0
					],
					[
						114272.727272727,
						3,
						0
					],
					[
						114545.454545454,
						1,
						0
					],
					[
						115090.909090909,
						0,
						0
					]
				],
				"typeOfSection": 0,
				"lengthInSteps": 16,
				"altAnim": false,
				"mustHitSection": true,
				"changeBPM": false,
				"bpm": 200
			},
			{
				"sectionNotes": [
					[
						115636.363636364,
						1,
						0
					],
					[
						115909.090909091,
						2,
						0
					],
					[
						116181.818181818,
						0,
						0
					],
					[
						116181.818181818,
						3,
						0
					],
					[
						115909.090909091,
						4,
						0
					],
					[
						116181.818181818,
						5,
						0
					],
					[
						116181.818181818,
						1,
						0
					],
					[
						117000,
						1,
						0
					],
					[
						117272.727272727,
						2,
						0
					],
					[
						117545.454545455,
						3,
						0
					]
				],
				"typeOfSection": 0,
				"lengthInSteps": 16,
				"altAnim": false,
				"mustHitSection": true,
				"changeBPM": false,
				"bpm": 200
			},
			{
				"sectionNotes": [
					[
						117818.181818182,
						1,
						0
					],
					[
						118909.090909091,
						2,
						0
					],
					[
						118636.363636364,
						0,
						0
					],
					[
						119181.818181818,
						3,
						0
					],
					[
						119454.545454545,
						1,
						0
					]
				],
				"typeOfSection": 0,
				"lengthInSteps": 16,
				"altAnim": false,
				"mustHitSection": true,
				"changeBPM": false,
				"bpm": 200
			},
			{
				"sectionNotes": [
					[
						120272.727272727,
						1,
						0
					],
					[
						120545.454545454,
						0,
						0
					],
					[
						120818.181818182,
						2,
						0
					],
					[
						121090.909090909,
						3,
						0
					],
					[
						121909.090909091,
						1,
						0
					]
				],
				"typeOfSection": 0,
				"lengthInSteps": 16,
				"altAnim": false,
				"mustHitSection": true,
				"changeBPM": false,
				"bpm": 200
			},
			{
				"sectionNotes": [
					[
						122181.818181818,
						0,
						0
					],
					[
						122454.545454545,
						2,
						0
					],
					[
						122727.272727273,
						3,
						0
					],
					[
						123545.454545454,
						1,
						0
					],
					[
						123818.181818182,
						2,
						136.363636363636
					],
					[
						124090.909090909,
						3,
						0
					]
				],
				"typeOfSection": 0,
				"lengthInSteps": 16,
				"altAnim": false,
				"mustHitSection": true,
				"changeBPM": false,
				"bpm": 200
			},
			{
				"sectionNotes": [
					[
						124363.636363636,
						1,
						0
					],
					[
						125727.272727273,
						3,
						0
					],
					[
						126000,
						0,
						0
					],
					[
						125181.818181818,
						0,
						0
					],
					[
						125454.545454545,
						2,
						0
					]
				],
				"typeOfSection": 0,
				"lengthInSteps": 16,
				"altAnim": false,
				"mustHitSection": false,
				"changeBPM": false,
				"bpm": 200
			},
			{
				"sectionNotes": [
					[
						126818.181818182,
						0,
						0
					],
					[
						127090.909090909,
						2,
						0
					],
					[
						127363.636363636,
						3,
						0
					],
					[
						127636.363636364,
						1,
						0
					],
					[
						128181.818181818,
						0,
						0
					]
				],
				"typeOfSection": 0,
				"lengthInSteps": 16,
				"altAnim": false,
				"mustHitSection": true,
				"changeBPM": false,
				"bpm": 200
			},
			{
				"sectionNotes": [
					[
						128727.272727273,
						1,
						409.090909090909
					]
				],
				"typeOfSection": 0,
				"lengthInSteps": 16,
				"altAnim": false,
				"mustHitSection": false,
				"changeBPM": false,
				"bpm": 200
			},
			{
				"sectionNotes": [],
				"typeOfSection": 0,
				"lengthInSteps": 16,
				"altAnim": false,
				"mustHitSection": false,
				"changeBPM": false,
				"bpm": 200
			},
			{
				"sectionNotes": [],
				"typeOfSection": 0,
				"lengthInSteps": 16,
				"altAnim": false,
				"mustHitSection": true,
				"changeBPM": false,
				"bpm": 200
			},
			{
				"sectionNotes": [],
				"typeOfSection": 0,
				"lengthInSteps": 16,
				"altAnim": false,
				"mustHitSection": true,
				"changeBPM": false,
				"bpm": 200
			},
			{
				"sectionNotes": [],
				"typeOfSection": 0,
				"lengthInSteps": 16,
				"altAnim": false,
				"mustHitSection": true,
				"changeBPM": false,
				"bpm": 200
			},
			{
				"sectionNotes": [],
				"typeOfSection": 0,
				"lengthInSteps": 16,
				"altAnim": false,
				"mustHitSection": true,
				"changeBPM": false,
				"bpm": 200
			},
			{
				"sectionNotes": [],
				"typeOfSection": 0,
				"lengthInSteps": 16,
				"altAnim": false,
				"mustHitSection": false,
				"changeBPM": false,
				"bpm": 200
			},
			{
				"sectionNotes": [],
				"typeOfSection": 0,
				"lengthInSteps": 16,
				"altAnim": false,
				"mustHitSection": false,
				"changeBPM": false,
				"bpm": 200
			},
			{
				"sectionNotes": [],
				"typeOfSection": 0,
				"lengthInSteps": 16,
				"altAnim": false,
				"mustHitSection": false,
				"changeBPM": false,
				"bpm": 200
			},
			{
				"sectionNotes": [],
				"typeOfSection": 0,
				"lengthInSteps": 16,
				"altAnim": false,
				"mustHitSection": false,
				"changeBPM": false,
				"bpm": 200
			},
			{
				"sectionNotes": [],
				"typeOfSection": 0,
				"lengthInSteps": 16,
				"altAnim": false,
				"mustHitSection": true,
				"changeBPM": false,
				"bpm": 200
			},
			{
				"sectionNotes": [],
				"typeOfSection": 0,
				"lengthInSteps": 16,
				"altAnim": false,
				"mustHitSection": true,
				"changeBPM": false,
				"bpm": 200
			},
			{
				"sectionNotes": [],
				"typeOfSection": 0,
				"lengthInSteps": 16,
				"altAnim": false,
				"mustHitSection": false,
				"changeBPM": false,
				"bpm": 200
			},
			{
				"sectionNotes": [],
				"typeOfSection": 0,
				"lengthInSteps": 16,
				"altAnim": false,
				"mustHitSection": false,
				"changeBPM": false,
				"bpm": 200
			},
			{
				"sectionNotes": [],
				"typeOfSection": 0,
				"lengthInSteps": 16,
				"altAnim": false,
				"mustHitSection": true,
				"changeBPM": false,
				"bpm": 200
			},
			{
				"sectionNotes": [],
				"typeOfSection": 0,
				"lengthInSteps": 16,
				"altAnim": false,
				"mustHitSection": true,
				"changeBPM": false,
				"bpm": 200
			},
			{
				"sectionNotes": [],
				"typeOfSection": 0,
				"lengthInSteps": 16,
				"altAnim": false,
				"mustHitSection": false,
				"changeBPM": false,
				"bpm": 200
			},
			{
				"sectionNotes": [],
				"typeOfSection": 0,
				"lengthInSteps": 16,
				"altAnim": false,
				"mustHitSection": false,
				"changeBPM": false,
				"bpm": 200
			},
			{
				"sectionNotes": [],
				"typeOfSection": 0,
				"lengthInSteps": 16,
				"altAnim": false,
				"mustHitSection": false,
				"changeBPM": false,
				"bpm": 200
			},
			{
				"sectionNotes": [],
				"typeOfSection": 0,
				"lengthInSteps": 16,
				"altAnim": false,
				"mustHitSection": false,
				"changeBPM": false,
				"bpm": 200
			},
			{
				"sectionNotes": [],
				"typeOfSection": 0,
				"lengthInSteps": 16,
				"altAnim": false,
				"mustHitSection": false,
				"changeBPM": false,
				"bpm": 200
			},
			{
				"sectionNotes": [],
				"typeOfSection": 0,
				"lengthInSteps": 16,
				"altAnim": false,
				"mustHitSection": false,
				"changeBPM": false,
				"bpm": 200
			},
			{
				"sectionNotes": [],
				"typeOfSection": 0,
				"lengthInSteps": 16,
				"altAnim": false,
				"mustHitSection": false,
				"changeBPM": false,
				"bpm": 200
			},
			{
				"sectionNotes": [],
				"typeOfSection": 0,
				"lengthInSteps": 16,
				"altAnim": false,
				"mustHitSection": false,
				"changeBPM": false,
				"bpm": 200
			},
			{
				"sectionNotes": [],
				"typeOfSection": 0,
				"lengthInSteps": 16,
				"altAnim": false,
				"mustHitSection": true,
				"changeBPM": false,
				"bpm": 200
			},
			{
				"sectionNotes": [],
				"typeOfSection": 0,
				"lengthInSteps": 16,
				"altAnim": false,
				"mustHitSection": true,
				"changeBPM": false,
				"bpm": 200
			},
			{
				"sectionNotes": [],
				"typeOfSection": 0,
				"lengthInSteps": 16,
				"altAnim": false,
				"mustHitSection": true,
				"changeBPM": false,
				"bpm": 200
			},
			{
				"sectionNotes": [],
				"typeOfSection": 0,
				"lengthInSteps": 16,
				"altAnim": false,
				"mustHitSection": true,
				"changeBPM": false,
				"bpm": 200
			},
			{
				"sectionNotes": [],
				"typeOfSection": 0,
				"lengthInSteps": 16,
				"altAnim": false,
				"mustHitSection": true,
				"changeBPM": false,
				"bpm": 200
			},
			{
				"sectionNotes": [],
				"typeOfSection": 0,
				"lengthInSteps": 16,
				"altAnim": false,
				"mustHitSection": true,
				"changeBPM": false,
				"bpm": 200
			},
			{
				"sectionNotes": [],
				"typeOfSection": 0,
				"lengthInSteps": 16,
				"altAnim": false,
				"mustHitSection": true,
				"changeBPM": false,
				"bpm": 200
			},
			{
				"sectionNotes": [],
				"typeOfSection": 0,
				"lengthInSteps": 16,
				"altAnim": false,
				"mustHitSection": true,
				"changeBPM": false,
				"bpm": 200
			},
			{
				"sectionNotes": [],
				"typeOfSection": 0,
				"lengthInSteps": 16,
				"altAnim": false,
				"mustHitSection": false,
				"changeBPM": false,
				"bpm": 200
			},
			{
				"sectionNotes": [],
				"typeOfSection": 0,
				"lengthInSteps": 16,
				"altAnim": false,
				"mustHitSection": true,
				"changeBPM": false,
				"bpm": 200
			},
			{
				"sectionNotes": [],
				"typeOfSection": 0,
				"lengthInSteps": 16,
				"altAnim": false,
				"mustHitSection": false,
				"changeBPM": false,
				"bpm": 200
			},
			{
				"sectionNotes": [],
				"typeOfSection": 0,
				"lengthInSteps": 16,
				"altAnim": false,
				"mustHitSection": false,
				"changeBPM": false,
				"bpm": 200
			},
			{
				"sectionNotes": [],
				"typeOfSection": 0,
				"lengthInSteps": 16,
				"altAnim": false,
				"mustHitSection": false,
				"changeBPM": false,
				"bpm": 200
			},
			{
				"sectionNotes": [],
				"typeOfSection": 0,
				"lengthInSteps": 16,
				"altAnim": false,
				"mustHitSection": false,
				"changeBPM": false,
				"bpm": 200
			},
			{
				"sectionNotes": [],
				"typeOfSection": 0,
				"lengthInSteps": 16,
				"altAnim": false,
				"mustHitSection": true,
				"changeBPM": false,
				"bpm": 200
			},
			{
				"sectionNotes": [],
				"typeOfSection": 0,
				"lengthInSteps": 16,
				"altAnim": false,
				"mustHitSection": true,
				"changeBPM": false,
				"bpm": 200
			},
			{
				"sectionNotes": [],
				"typeOfSection": 0,
				"lengthInSteps": 16,
				"altAnim": false,
				"mustHitSection": true,
				"changeBPM": false,
				"bpm": 200
			},
			{
				"sectionNotes": [],
				"typeOfSection": 0,
				"lengthInSteps": 16,
				"altAnim": false,
				"mustHitSection": true,
				"changeBPM": false,
				"bpm": 200
			},
			{
				"sectionNotes": [],
				"typeOfSection": 0,
				"lengthInSteps": 16,
				"altAnim": false,
				"mustHitSection": false,
				"changeBPM": false,
				"bpm": 200
			},
			{
				"sectionNotes": [],
				"typeOfSection": 0,
				"lengthInSteps": 16,
				"altAnim": false,
				"mustHitSection": false,
				"changeBPM": false,
				"bpm": 200
			},
			{
				"sectionNotes": [],
				"typeOfSection": 0,
				"lengthInSteps": 16,
				"altAnim": false,
				"mustHitSection": false,
				"changeBPM": false,
				"bpm": 200
			},
			{
				"sectionNotes": [],
				"typeOfSection": 0,
				"lengthInSteps": 16,
				"altAnim": false,
				"mustHitSection": false,
				"changeBPM": false,
				"bpm": 200
			},
			{
				"sectionNotes": [],
				"typeOfSection": 0,
				"lengthInSteps": 16,
				"altAnim": false,
				"mustHitSection": true,
				"changeBPM": false,
				"bpm": 200
			},
			{
				"sectionNotes": [],
				"typeOfSection": 0,
				"lengthInSteps": 16,
				"altAnim": false,
				"mustHitSection": true,
				"changeBPM": false,
				"bpm": 200
			},
			{
				"sectionNotes": [],
				"typeOfSection": 0,
				"lengthInSteps": 16,
				"altAnim": false,
				"mustHitSection": true,
				"changeBPM": false,
				"bpm": 200
			},
			{
				"sectionNotes": [],
				"typeOfSection": 0,
				"lengthInSteps": 16,
				"altAnim": false,
				"mustHitSection": true,
				"changeBPM": false,
				"bpm": 200
			},
			{
				"sectionNotes": [],
				"typeOfSection": 0,
				"lengthInSteps": 16,
				"altAnim": false,
				"mustHitSection": true,
				"changeBPM": false,
				"bpm": 200
			},
			{
				"sectionNotes": [],
				"typeOfSection": 0,
				"lengthInSteps": 16,
				"altAnim": false,
				"mustHitSection": true,
				"changeBPM": false,
				"bpm": 200
			},
			{
				"sectionNotes": [],
				"typeOfSection": 0,
				"lengthInSteps": 16,
				"altAnim": false,
				"mustHitSection": true,
				"changeBPM": false,
				"bpm": 200
			},
			{
				"sectionNotes": [],
				"typeOfSection": 0,
				"lengthInSteps": 16,
				"altAnim": false,
				"mustHitSection": true,
				"changeBPM": false,
				"bpm": 200
			},
			{
				"sectionNotes": [],
				"typeOfSection": 0,
				"lengthInSteps": 16,
				"altAnim": false,
				"mustHitSection": false,
				"changeBPM": false,
				"bpm": 200
			},
			{
				"sectionNotes": [],
				"typeOfSection": 0,
				"lengthInSteps": 16,
				"altAnim": false,
				"mustHitSection": false,
				"changeBPM": false,
				"bpm": 200
			},
			{
				"sectionNotes": [],
				"typeOfSection": 0,
				"lengthInSteps": 16,
				"altAnim": false,
				"mustHitSection": false,
				"changeBPM": false,
				"bpm": 200
			},
			{
				"sectionNotes": [],
				"typeOfSection": 0,
				"lengthInSteps": 16,
				"altAnim": false,
				"mustHitSection": false,
				"changeBPM": false,
				"bpm": 200
			},
			{
				"sectionNotes": [],
				"typeOfSection": 0,
				"lengthInSteps": 16,
				"altAnim": false,
				"mustHitSection": true,
				"changeBPM": false,
				"bpm": 200
			},
			{
				"sectionNotes": [],
				"typeOfSection": 0,
				"lengthInSteps": 16,
				"altAnim": false,
				"mustHitSection": true,
				"changeBPM": false,
				"bpm": 200
			},
			{
				"sectionNotes": [],
				"typeOfSection": 0,
				"lengthInSteps": 16,
				"altAnim": false,
				"mustHitSection": false,
				"changeBPM": false,
				"bpm": 200
			},
			{
				"sectionNotes": [],
				"typeOfSection": 0,
				"lengthInSteps": 16,
				"altAnim": false,
				"mustHitSection": false,
				"changeBPM": false,
				"bpm": 200
			},
			{
				"sectionNotes": [],
				"typeOfSection": 0,
				"lengthInSteps": 16,
				"altAnim": false,
				"mustHitSection": true,
				"changeBPM": false,
				"bpm": 200
			},
			{
				"sectionNotes": [],
				"typeOfSection": 0,
				"lengthInSteps": 16,
				"altAnim": false,
				"mustHitSection": true,
				"changeBPM": false,
				"bpm": 200
			},
			{
				"sectionNotes": [],
				"typeOfSection": 0,
				"lengthInSteps": 16,
				"altAnim": false,
				"mustHitSection": false,
				"changeBPM": false,
				"bpm": 200
			},
			{
				"sectionNotes": [],
				"typeOfSection": 0,
				"lengthInSteps": 16,
				"altAnim": false,
				"mustHitSection": false,
				"changeBPM": false,
				"bpm": 200
			},
			{
				"sectionNotes": [],
				"typeOfSection": 0,
				"lengthInSteps": 16,
				"altAnim": false,
				"mustHitSection": true,
				"changeBPM": false,
				"bpm": 200
			},
			{
				"sectionNotes": [],
				"typeOfSection": 0,
				"lengthInSteps": 16,
				"altAnim": false,
				"mustHitSection": false,
				"changeBPM": false,
				"bpm": 200
			},
			{
				"sectionNotes": [],
				"typeOfSection": 0,
				"lengthInSteps": 16,
				"altAnim": false,
				"mustHitSection": false,
				"changeBPM": false,
				"bpm": 200
			},
			{
				"sectionNotes": [],
				"typeOfSection": 0,
				"lengthInSteps": 16,
				"altAnim": false,
				"mustHitSection": false,
				"changeBPM": false,
				"bpm": 200
			},
			{
				"sectionNotes": [],
				"typeOfSection": 0,
				"lengthInSteps": 16,
				"altAnim": false,
				"mustHitSection": false,
				"changeBPM": false,
				"bpm": 200
			},
			{
				"sectionNotes": [],
				"typeOfSection": 0,
				"lengthInSteps": 16,
				"altAnim": false,
				"mustHitSection": false,
				"changeBPM": false,
				"bpm": 200
			},
			{
				"sectionNotes": [],
				"typeOfSection": 0,
				"lengthInSteps": 16,
				"altAnim": false,
				"mustHitSection": false,
				"changeBPM": false,
				"bpm": 200
			},
			{
				"sectionNotes": [],
				"typeOfSection": 0,
				"lengthInSteps": 16,
				"altAnim": false,
				"mustHitSection": false,
				"changeBPM": false,
				"bpm": 200
			},
			{
				"sectionNotes": [],
				"typeOfSection": 0,
				"lengthInSteps": 16,
				"altAnim": false,
				"mustHitSection": false,
				"changeBPM": false,
				"bpm": 200
			},
			{
				"sectionNotes": [],
				"typeOfSection": 0,
				"lengthInSteps": 16,
				"altAnim": false,
				"mustHitSection": true,
				"changeBPM": false,
				"bpm": 200
			},
			{
				"sectionNotes": [],
				"typeOfSection": 0,
				"lengthInSteps": 16,
				"altAnim": false,
				"mustHitSection": true,
				"changeBPM": false,
				"bpm": 200
			},
			{
				"sectionNotes": [],
				"typeOfSection": 0,
				"lengthInSteps": 16,
				"altAnim": false,
				"mustHitSection": true,
				"changeBPM": false,
				"bpm": 200
			},
			{
				"sectionNotes": [],
				"typeOfSection": 0,
				"lengthInSteps": 16,
				"altAnim": false,
				"mustHitSection": true,
				"changeBPM": false,
				"bpm": 200
			},
			{
				"sectionNotes": [],
				"typeOfSection": 0,
				"lengthInSteps": 16,
				"altAnim": false,
				"mustHitSection": true,
				"changeBPM": false,
				"bpm": 200
			},
			{
				"sectionNotes": [],
				"typeOfSection": 0,
				"lengthInSteps": 16,
				"altAnim": false,
				"mustHitSection": true,
				"changeBPM": false,
				"bpm": 200
			},
			{
				"sectionNotes": [],
				"typeOfSection": 0,
				"lengthInSteps": 16,
				"altAnim": false,
				"mustHitSection": true,
				"changeBPM": false,
				"bpm": 200
			},
			{
				"sectionNotes": [],
				"typeOfSection": 0,
				"lengthInSteps": 16,
				"altAnim": false,
				"mustHitSection": true,
				"changeBPM": false,
				"bpm": 200
			},
			{
				"sectionNotes": [],
				"typeOfSection": 0,
				"lengthInSteps": 16,
				"altAnim": false,
				"mustHitSection": false,
				"changeBPM": false,
				"bpm": 200
			},
			{
				"sectionNotes": [],
				"typeOfSection": 0,
				"lengthInSteps": 16,
				"altAnim": false,
				"mustHitSection": false,
				"changeBPM": false,
				"bpm": 200
			},
			{
				"sectionNotes": [],
				"typeOfSection": 0,
				"lengthInSteps": 16,
				"altAnim": false,
				"mustHitSection": false,
				"changeBPM": false,
				"bpm": 200
			},
			{
				"sectionNotes": [],
				"typeOfSection": 0,
				"lengthInSteps": 16,
				"altAnim": false,
				"mustHitSection": false,
				"changeBPM": false,
				"bpm": 200
			},
			{
				"sectionNotes": [],
				"typeOfSection": 0,
				"lengthInSteps": 16,
				"altAnim": false,
				"mustHitSection": false,
				"changeBPM": false,
				"bpm": 200
			},
			{
				"lengthInSteps": 16,
				"typeOfSection": 0,
				"sectionNotes": [],
				"altAnim": false,
				"bpm": 200,
				"changeBPM": false,
				"mustHitSection": false
			},
			{
				"sectionNotes": [],
				"typeOfSection": 0,
				"lengthInSteps": 16,
				"altAnim": false,
				"mustHitSection": true,
				"changeBPM": false,
				"bpm": 200
			},
			{
				"lengthInSteps": 16,
				"typeOfSection": 0,
				"sectionNotes": [],
				"altAnim": false,
				"bpm": 200,
				"changeBPM": false,
				"mustHitSection": true
			},
			{
				"lengthInSteps": 16,
				"typeOfSection": 0,
				"sectionNotes": [],
				"altAnim": false,
				"bpm": 200,
				"changeBPM": false,
				"mustHitSection": true
			},
			{
				"lengthInSteps": 16,
				"typeOfSection": 0,
				"sectionNotes": [],
				"altAnim": false,
				"bpm": 200,
				"changeBPM": false,
				"mustHitSection": true
			},
			{
				"lengthInSteps": 16,
				"typeOfSection": 0,
				"sectionNotes": [],
				"altAnim": false,
				"bpm": 200,
				"changeBPM": false,
				"mustHitSection": true
			},
			{
				"lengthInSteps": 16,
				"typeOfSection": 0,
				"sectionNotes": [],
				"altAnim": false,
				"bpm": 200,
				"changeBPM": false,
				"mustHitSection": true
			},
			{
				"lengthInSteps": 16,
				"typeOfSection": 0,
				"sectionNotes": [],
				"altAnim": false,
				"bpm": 200,
				"changeBPM": false,
				"mustHitSection": true
			},
			{
				"lengthInSteps": 16,
				"typeOfSection": 0,
				"sectionNotes": [],
				"altAnim": false,
				"bpm": 200,
				"changeBPM": false,
				"mustHitSection": true
			},
			{
				"lengthInSteps": 16,
				"typeOfSection": 0,
				"sectionNotes": [],
				"altAnim": false,
				"bpm": 200,
				"changeBPM": false,
				"mustHitSection": true
			},
			{
				"lengthInSteps": 16,
				"typeOfSection": 0,
				"sectionNotes": [],
				"altAnim": false,
				"bpm": 200,
				"changeBPM": false,
				"mustHitSection": true
			},
			{
				"lengthInSteps": 16,
				"typeOfSection": 0,
				"sectionNotes": [],
				"altAnim": false,
				"bpm": 200,
				"changeBPM": false,
				"mustHitSection": true
			},
			{
				"lengthInSteps": 16,
				"typeOfSection": 0,
				"sectionNotes": [],
				"altAnim": false,
				"bpm": 200,
				"changeBPM": false,
				"mustHitSection": true
			},
			{
				"lengthInSteps": 16,
				"typeOfSection": 0,
				"sectionNotes": [],
				"altAnim": false,
				"bpm": 200,
				"changeBPM": false,
				"mustHitSection": true
			},
			{
				"lengthInSteps": 16,
				"typeOfSection": 0,
				"sectionNotes": [],
				"altAnim": false,
				"bpm": 200,
				"changeBPM": false,
				"mustHitSection": true
			},
			{
				"sectionNotes": [],
				"typeOfSection": 0,
				"lengthInSteps": 16,
				"altAnim": false,
				"mustHitSection": true,
				"changeBPM": false,
				"bpm": 200
			},
			{
				"lengthInSteps": 16,
				"typeOfSection": 0,
				"sectionNotes": [],
				"altAnim": false,
				"bpm": 200,
				"changeBPM": false,
				"mustHitSection": true
			},
			{
				"lengthInSteps": 16,
				"typeOfSection": 0,
				"sectionNotes": [],
				"altAnim": false,
				"bpm": 200,
				"changeBPM": false,
				"mustHitSection": true
			},
			{
				"lengthInSteps": 16,
				"typeOfSection": 0,
				"sectionNotes": [],
				"altAnim": false,
				"bpm": 200,
				"changeBPM": false,
				"mustHitSection": true
			},
			{
				"lengthInSteps": 16,
				"typeOfSection": 0,
				"sectionNotes": [],
				"altAnim": false,
				"bpm": 200,
				"changeBPM": false,
				"mustHitSection": true
			},
			{
				"sectionNotes": [],
				"typeOfSection": 0,
				"lengthInSteps": 16,
				"altAnim": false,
				"mustHitSection": true,
				"changeBPM": false,
				"bpm": 200
			},
			{
				"sectionNotes": [],
				"typeOfSection": 0,
				"lengthInSteps": 16,
				"altAnim": false,
				"mustHitSection": true,
				"changeBPM": false,
				"bpm": 200
			},
			{
				"sectionNotes": [],
				"typeOfSection": 0,
				"lengthInSteps": 16,
				"altAnim": false,
				"mustHitSection": true,
				"changeBPM": false,
				"bpm": 200
			},
			{
				"sectionNotes": [],
				"typeOfSection": 0,
				"lengthInSteps": 16,
				"altAnim": false,
				"mustHitSection": true,
				"changeBPM": false,
				"bpm": 200
			},
			{
				"sectionNotes": [],
				"typeOfSection": 0,
				"lengthInSteps": 16,
				"altAnim": false,
				"mustHitSection": true,
				"changeBPM": false,
				"bpm": 200
			},
			{
				"lengthInSteps": 16,
				"typeOfSection": 0,
				"sectionNotes": [],
				"altAnim": false,
				"bpm": 200,
				"changeBPM": false,
				"mustHitSection": true
			},
			{
				"lengthInSteps": 16,
				"typeOfSection": 0,
				"sectionNotes": [],
				"altAnim": false,
				"bpm": 200,
				"changeBPM": false,
				"mustHitSection": true
			},
			{
				"lengthInSteps": 16,
				"typeOfSection": 0,
				"sectionNotes": [],
				"altAnim": false,
				"bpm": 200,
				"changeBPM": false,
				"mustHitSection": true
			},
			{
				"sectionNotes": [],
				"typeOfSection": 0,
				"lengthInSteps": 16,
				"altAnim": false,
				"mustHitSection": true,
				"changeBPM": false,
				"bpm": 200
			},
			{
				"sectionNotes": [],
				"typeOfSection": 0,
				"lengthInSteps": 16,
				"altAnim": false,
				"mustHitSection": true,
				"changeBPM": false,
				"bpm": 200
			},
			{
				"lengthInSteps": 16,
				"typeOfSection": 0,
				"sectionNotes": [],
				"altAnim": false,
				"bpm": 200,
				"changeBPM": false,
				"mustHitSection": true
			},
			{
				"sectionNotes": [],
				"typeOfSection": 0,
				"lengthInSteps": 16,
				"altAnim": false,
				"mustHitSection": true,
				"changeBPM": false,
				"bpm": 200
			},
			{
				"lengthInSteps": 16,
				"typeOfSection": 0,
				"sectionNotes": [],
				"altAnim": false,
				"bpm": 200,
				"changeBPM": false,
				"mustHitSection": true
			},
			{
				"lengthInSteps": 16,
				"typeOfSection": 0,
				"sectionNotes": [],
				"altAnim": false,
				"bpm": 200,
				"changeBPM": false,
				"mustHitSection": true
			},
			{
				"sectionNotes": [],
				"typeOfSection": 0,
				"lengthInSteps": 16,
				"altAnim": false,
				"mustHitSection": true,
				"changeBPM": false,
				"bpm": 200
			},
			{
				"sectionNotes": [],
				"typeOfSection": 0,
				"lengthInSteps": 16,
				"altAnim": false,
				"mustHitSection": true,
				"changeBPM": false,
				"bpm": 200
			},
			{
				"sectionNotes": [],
				"typeOfSection": 0,
				"lengthInSteps": 16,
				"altAnim": false,
				"mustHitSection": true,
				"changeBPM": false,
				"bpm": 200
			},
			{
				"lengthInSteps": 16,
				"typeOfSection": 0,
				"sectionNotes": [],
				"altAnim": false,
				"bpm": 200,
				"changeBPM": false,
				"mustHitSection": true
			},
			{
				"sectionNotes": [],
				"typeOfSection": 0,
				"lengthInSteps": 16,
				"altAnim": false,
				"mustHitSection": true,
				"changeBPM": false,
				"bpm": 200
			},
			{
				"sectionNotes": [],
				"typeOfSection": 0,
				"lengthInSteps": 16,
				"altAnim": false,
				"mustHitSection": true,
				"changeBPM": false,
				"bpm": 200
			},
			{
				"lengthInSteps": 16,
				"typeOfSection": 0,
				"sectionNotes": [],
				"altAnim": false,
				"gfSection": false,
				"bpm": 200,
				"changeBPM": false,
				"mustHitSection": true
			},
			{
				"sectionNotes": [],
				"typeOfSection": 0,
				"lengthInSteps": 16,
				"gfSection": false,
				"altAnim": false,
				"mustHitSection": true,
				"changeBPM": false,
				"bpm": 200
			},
			{
				"sectionNotes": [],
				"typeOfSection": 0,
				"lengthInSteps": 16,
				"gfSection": false,
				"altAnim": false,
				"mustHitSection": true,
				"changeBPM": false,
				"bpm": 200
			},
			{
				"sectionNotes": [],
				"typeOfSection": 0,
				"lengthInSteps": 16,
				"gfSection": false,
				"altAnim": false,
				"mustHitSection": true,
				"changeBPM": false,
				"bpm": 200
			},
			{
				"sectionNotes": [],
				"typeOfSection": 0,
				"lengthInSteps": 16,
				"gfSection": false,
				"altAnim": false,
				"mustHitSection": true,
				"changeBPM": false,
				"bpm": 200
			},
			{
				"lengthInSteps": 16,
				"typeOfSection": 0,
				"sectionNotes": [],
				"altAnim": false,
				"gfSection": false,
				"bpm": 200,
				"changeBPM": false,
				"mustHitSection": true
			},
			{
				"lengthInSteps": 16,
				"typeOfSection": 0,
				"sectionNotes": [],
				"altAnim": false,
				"gfSection": false,
				"bpm": 200,
				"changeBPM": false,
				"mustHitSection": true
			},
			{
				"lengthInSteps": 16,
				"typeOfSection": 0,
				"sectionNotes": [],
				"altAnim": false,
				"gfSection": false,
				"bpm": 200,
				"changeBPM": false,
				"mustHitSection": true
			},
			{
				"lengthInSteps": 16,
				"typeOfSection": 0,
				"sectionNotes": [],
				"altAnim": false,
				"gfSection": false,
				"bpm": 200,
				"changeBPM": false,
				"mustHitSection": true
			},
			{
				"sectionBeats": 4,
				"sectionNotes": [],
				"typeOfSection": 0,
				"gfSection": false,
				"altAnim": false,
				"mustHitSection": true,
				"changeBPM": false,
				"bpm": 200
			},
			{
				"sectionBeats": 4,
				"sectionNotes": [],
				"typeOfSection": 0,
				"gfSection": false,
				"altAnim": false,
				"mustHitSection": true,
				"changeBPM": false,
				"bpm": 110
			},
			{
				"sectionBeats": 4,
				"sectionNotes": [],
				"typeOfSection": 0,
				"gfSection": false,
				"altAnim": false,
				"mustHitSection": true,
				"changeBPM": false,
				"bpm": 110
			},
			{
				"sectionBeats": 4,
				"sectionNotes": [],
				"typeOfSection": 0,
				"gfSection": false,
				"altAnim": false,
				"mustHitSection": true,
				"changeBPM": false,
				"bpm": 110
			},
			{
				"sectionBeats": 4,
				"sectionNotes": [],
				"typeOfSection": 0,
				"gfSection": false,
				"altAnim": false,
				"mustHitSection": true,
				"changeBPM": false,
				"bpm": 110
			},
			{
				"sectionBeats": 4,
				"sectionNotes": [],
				"typeOfSection": 0,
				"gfSection": false,
				"altAnim": false,
				"mustHitSection": true,
				"changeBPM": false,
				"bpm": 110
			},
			{
				"sectionBeats": 4,
				"sectionNotes": [],
				"typeOfSection": 0,
				"gfSection": false,
				"altAnim": false,
				"mustHitSection": true,
				"changeBPM": false,
				"bpm": 110
			},
			{
				"sectionBeats": 4,
				"sectionNotes": [],
				"typeOfSection": 0,
				"gfSection": false,
				"altAnim": false,
				"mustHitSection": true,
				"changeBPM": false,
				"bpm": 110
			},
			{
				"sectionBeats": 4,
				"sectionNotes": [],
				"typeOfSection": 0,
				"gfSection": false,
				"altAnim": false,
				"mustHitSection": true,
				"changeBPM": false,
				"bpm": 110
			},
			{
				"sectionBeats": 4,
				"sectionNotes": [],
				"typeOfSection": 0,
				"gfSection": false,
				"altAnim": false,
				"mustHitSection": true,
				"changeBPM": false,
				"bpm": 110
			},
			{
				"gfSection": false,
				"altAnim": false,
				"typeOfSection": 0,
				"sectionNotes": [],
				"bpm": 110,
				"sectionBeats": 4,
				"changeBPM": false,
				"mustHitSection": true
			},
			{
				"gfSection": false,
				"altAnim": false,
				"typeOfSection": 0,
				"sectionNotes": [],
				"bpm": 110,
				"sectionBeats": 4,
				"changeBPM": false,
				"mustHitSection": true
			}
		],
		"player3": null,
		"initialSpeed": 1.575,
		"sliderVelocities": null,
		"song": "let me through",
		"stage": "Through",
		"validScore": true,
		"needsVoices": true,
		"speed": 3.5,
		"bpm": 110
	}
}